[
  {
    "id": "b5a4e8f2-1c3d-4e5f-8a9b-2d4f6h8j0l2n",
    "year": 0,
    "month": 1,
    "day": 1,
    "text": "Event description goes here",
    "image": {
      "url": "https://example.com/image.jpg",
      "local": "images/filename.webp"
    },
    "source": {
      "text": "Author. (Year). Article Title. Publisher.",
      "url": "https://example.com/source"
    }
  },
  {
    "id": "c6b5f9g3-2d4e-5f6g-9b0c-3e5g7i9k1m3o",
    "year": 0,
    "month": 1,
    "day": 1,
    "text": "Event description goes here",
    "image": {
      "url": "https://example.com/image.jpg",
      "local": "images/filename.webp"
    },
    "source": {
      "text": "Author. (Year). Article Title. Publisher.",
      "url": "https://example.com/source"
    }
  }
]
